README.md
setup.py
src/dauth/__init__.py
src/dauth/auth.py
src/dauth.egg-info/PKG-INFO
src/dauth.egg-info/SOURCES.txt
src/dauth.egg-info/dependency_links.txt
src/dauth.egg-info/top_level.txt