Metadata-Version: 2.1
Name: dauth
Version: 0.1
Summary: FastAPI ABAC authorization realization
